dottable_dict/__init__.py
dottable_dict/dottable_dict.py
dottable_dict-0.0.5.1.dist-info/LICENSE
dottable_dict-0.0.5.1.dist-info/METADATA
dottable_dict-0.0.5.1.dist-info/WHEEL
dottable_dict-0.0.5.1.dist-info/top_level.txt
dottable_dict-0.0.5.1.dist-info/RECORD
