Metadata-Version: 2.1
Name: dottable_dict
Version: 0.0.5.1
Summary: Your everyday dictionary, with the special ability to be accessed using dot-notation
Author-email: Yuval Dotan <ydotan.tech@gmail.com>
Project-URL: Homepage, https://github.com/yuvdo/dottable_dict
Project-URL: Issues, https://github.com/yuvdo/dottable_dict/issues
Classifier: Programming Language :: Python :: 3
Classifier: License :: OSI Approved :: MIT License
Classifier: Operating System :: OS Independent
Requires-Python: >=3.10
License-File: LICENSE
